opsmanager/__init__.py
opsmanager/auth.py
opsmanager/client.py
opsmanager/errors.py
opsmanager/network.py
opsmanager/pagination.py
opsmanager/py.typed
opsmanager/types.py
opsmanager/services/__init__.py
opsmanager/services/alerts.py
opsmanager/services/base.py
opsmanager/services/clusters.py
opsmanager/services/deployments.py
opsmanager/services/measurements.py
opsmanager/services/organizations.py
opsmanager/services/performance_advisor.py
opsmanager/services/projects.py
opsmanager-0.2.1.dist-info/licenses/LICENSE
opsmanager-0.2.1.dist-info/METADATA
opsmanager-0.2.1.dist-info/WHEEL
opsmanager-0.2.1.dist-info/top_level.txt
opsmanager-0.2.1.dist-info/RECORD
