Metadata-Version: 2.4
Name: opsmanager
Version: 0.2.1
Summary: Python client library for MongoDB Ops Manager API
Author: Frank Snow
Maintainer: Frank Snow
License-Expression: Apache-2.0
Project-URL: Homepage, https://github.com/fsnow/python-mongodb-ops-manager
Project-URL: Documentation, https://github.com/fsnow/python-mongodb-ops-manager#readme
Project-URL: Repository, https://github.com/fsnow/python-mongodb-ops-manager.git
Project-URL: Issues, https://github.com/fsnow/python-mongodb-ops-manager/issues
Keywords: mongodb,ops-manager,cloud-manager,api,client,monitoring,database
Classifier: Development Status :: 4 - Beta
Classifier: Intended Audience :: Developers
Classifier: Intended Audience :: System Administrators
Classifier: Operating System :: OS Independent
Classifier: Programming Language :: Python :: 3
Classifier: Programming Language :: Python :: 3.9
Classifier: Programming Language :: Python :: 3.10
Classifier: Programming Language :: Python :: 3.11
Classifier: Programming Language :: Python :: 3.12
Classifier: Programming Language :: Python :: 3.13
Classifier: Programming Language :: Python :: 3.14
Classifier: Topic :: Database
Classifier: Topic :: System :: Monitoring
Classifier: Topic :: System :: Systems Administration
Classifier: Typing :: Typed
Requires-Python: >=3.9
License-File: LICENSE
Requires-Dist: requests>=2.28.0
Provides-Extra: dev
Requires-Dist: pytest>=7.0.0; extra == "dev"
Requires-Dist: pytest-cov>=4.0.0; extra == "dev"
Requires-Dist: black>=23.0.0; extra == "dev"
Requires-Dist: isort>=5.12.0; extra == "dev"
Requires-Dist: mypy>=1.0.0; extra == "dev"
Requires-Dist: ruff>=0.1.0; extra == "dev"
Requires-Dist: types-requests>=2.28.0; extra == "dev"
Provides-Extra: docs
Requires-Dist: sphinx>=6.0.0; extra == "docs"
Requires-Dist: sphinx-rtd-theme>=1.2.0; extra == "docs"
Dynamic: license-file
